open_parser/__init__.py
open_parser/base.py
open_parser-0.0.7.dist-info/METADATA
open_parser-0.0.7.dist-info/WHEEL
open_parser-0.0.7.dist-info/RECORD
